google/shopping/merchant_lfp/__init__.py
google/shopping/merchant_lfp/gapic_version.py
google/shopping/merchant_lfp/py.typed
google/shopping/merchant_lfp_v1/__init__.py
google/shopping/merchant_lfp_v1/gapic_metadata.json
google/shopping/merchant_lfp_v1/gapic_version.py
google/shopping/merchant_lfp_v1/py.typed
google/shopping/merchant_lfp_v1/services/__init__.py
google/shopping/merchant_lfp_v1/services/lfp_inventory_service/__init__.py
google/shopping/merchant_lfp_v1/services/lfp_inventory_service/async_client.py
google/shopping/merchant_lfp_v1/services/lfp_inventory_service/client.py
google/shopping/merchant_lfp_v1/services/lfp_inventory_service/transports/__init__.py
google/shopping/merchant_lfp_v1/services/lfp_inventory_service/transports/base.py
google/shopping/merchant_lfp_v1/services/lfp_inventory_service/transports/grpc.py
google/shopping/merchant_lfp_v1/services/lfp_inventory_service/transports/grpc_asyncio.py
google/shopping/merchant_lfp_v1/services/lfp_inventory_service/transports/rest.py
google/shopping/merchant_lfp_v1/services/lfp_inventory_service/transports/rest_base.py
google/shopping/merchant_lfp_v1/services/lfp_merchant_state_service/__init__.py
google/shopping/merchant_lfp_v1/services/lfp_merchant_state_service/async_client.py
google/shopping/merchant_lfp_v1/services/lfp_merchant_state_service/client.py
google/shopping/merchant_lfp_v1/services/lfp_merchant_state_service/transports/__init__.py
google/shopping/merchant_lfp_v1/services/lfp_merchant_state_service/transports/base.py
google/shopping/merchant_lfp_v1/services/lfp_merchant_state_service/transports/grpc.py
google/shopping/merchant_lfp_v1/services/lfp_merchant_state_service/transports/grpc_asyncio.py
google/shopping/merchant_lfp_v1/services/lfp_merchant_state_service/transports/rest.py
google/shopping/merchant_lfp_v1/services/lfp_merchant_state_service/transports/rest_base.py
google/shopping/merchant_lfp_v1/services/lfp_sale_service/__init__.py
google_shopping_merchant_lfp-1.2.0.dist-info/licenses/LICENSE
google_shopping_merchant_lfp-1.2.0.dist-info/METADATA
google_shopping_merchant_lfp-1.2.0.dist-info/WHEEL
google_shopping_merchant_lfp-1.2.0.dist-info/top_level.txt
google_shopping_merchant_lfp-1.2.0.dist-info/RECORD
